saxpy/__init__.py
saxpy/alphabet.py
saxpy/discord.py
saxpy/distance.py
saxpy/hotsax.py
saxpy/paa.py
saxpy/sax.py
saxpy/strfunc.py
saxpy/visit_registry.py
saxpy/znorm.py
saxpy-1.0.1.dev167.dist-info/DESCRIPTION.rst
saxpy-1.0.1.dev167.dist-info/METADATA
saxpy-1.0.1.dev167.dist-info/RECORD
saxpy-1.0.1.dev167.dist-info/WHEEL
saxpy-1.0.1.dev167.dist-info/metadata.json
saxpy-1.0.1.dev167.dist-info/pbr.json
saxpy-1.0.1.dev167.dist-info/top_level.txt
