Metadata-Version: 2.0
Name: saxpy
Version: 1.0.1.dev167
Summary: SAX, HOTSAX, EMMA implementations for Python
Home-page: https://github.com/seninp/saxpy.git
Author: Pavel Senin
Author-email: seninp@gmail.org
License: GPL2
Platform: UNKNOWN
Classifier: Development Status :: 4 - Beta
Classifier: Environment :: Console
Classifier: Intended Audience :: Developers
Classifier: Intended Audience :: Information Technology
Classifier: Operating System :: OS Independent
Classifier: Programming Language :: Python
Requires-Dist: codecov
Requires-Dist: numpy
Requires-Dist: pytest
Requires-Dist: pytest-cov
